[
    {
        "component_name": "Weapon",
        "root_vs": "9684c4091fc9e35a",
        "draw_vb": "e5672032",
        "position_vb": "27527c44",
        "blend_vb": "6f2d0bd2",
        "texcoord_vb": "7f259d83",
        "ib": "cff7ddad",
        "object_indexes": [
            0
        ],
        "object_classifications": [
            "A"
        ],
        "texture_hashes": [
            [
                [
                    "Diffuse",
                    ".dds",
                    "49023bf7"
                ],
                [
                    "NormalMap",
                    ".dds",
                    "faab2eb0"
                ],
                [
                    "MaterialMap",
                    ".dds",
                    "26fa9567"
                ],
                [
                    "LightMap",
                    ".dds",
                    "4834fc6d"
                ]
            ]
        ]
    }
]